whocovid19db/__init__.py
whocovid19db-0.0.1.dist-info/LICENSE.txt
whocovid19db-0.0.1.dist-info/WHEEL
whocovid19db-0.0.1.dist-info/METADATA
whocovid19db-0.0.1.dist-info/RECORD
